flask_mongoengine/__init__.py
flask_mongoengine/_version.py
flask_mongoengine/connection.py
flask_mongoengine/db_fields.py
flask_mongoengine/decorators.py
flask_mongoengine/documents.py
flask_mongoengine/json.py
flask_mongoengine/panels.py
flask_mongoengine/sessions.py
flask_mongoengine/pagination/__init__.py
flask_mongoengine/pagination/abc_pagination.py
flask_mongoengine/pagination/basic_pagination.py
flask_mongoengine/pagination/keyset_pagination.py
flask_mongoengine/pagination/list_field_pagination.py
flask_mongoengine/templates/panels/mongo-panel.html
flask_mongoengine/wtf/__init__.py
flask_mongoengine/wtf/fields.py
flask_mongoengine/wtf/models.py
flask_mongoengine/wtf/orm.py
flask_mongoengine_3-1.1.0.dist-info/AUTHORS.md
flask_mongoengine_3-1.1.0.dist-info/LICENSE.md
flask_mongoengine_3-1.1.0.dist-info/METADATA
flask_mongoengine_3-1.1.0.dist-info/WHEEL
flask_mongoengine_3-1.1.0.dist-info/top_level.txt
flask_mongoengine_3-1.1.0.dist-info/RECORD
